d1_client/__init__.py
d1_client/baseclient.py
d1_client/baseclient_1_1.py
d1_client/baseclient_1_2.py
d1_client/baseclient_2_0.py
d1_client/cnclient.py
d1_client/cnclient_1_1.py
d1_client/cnclient_1_2.py
d1_client/cnclient_2_0.py
d1_client/command_line.py
d1_client/d1client.py
d1_client/mnclient.py
d1_client/mnclient_1_1.py
d1_client/mnclient_1_2.py
d1_client/mnclient_2_0.py
d1_client/session.py
d1_client/solr_client.py
d1_client/util.py
d1_client/aio/__init__.py
d1_client/aio/async_client.py
d1_client/aio/command_line.py
d1_client/aio/util.py
d1_client/aio/iter/__init__.py
d1_client/aio/iter/base_async.py
d1_client/aio/iter/eventlog_async.py
d1_client/aio/iter/eventlog_cmd.py
d1_client/aio/iter/objectlist_async.py
d1_client/aio/iter/objectlist_cmd.py
d1_client/aio/iter/test.py
d1_client/iter/__init__.py
d1_client/iter/base_multi.py
d1_client/iter/logrecord.py
d1_client/iter/logrecord_multi.py
d1_client/iter/node.py
d1_client/iter/objectlist.py
d1_client/iter/objectlist_multi.py
d1_client/iter/sysmeta_multi.py
d1_client/tests/__init__.py
d1_client/tests/shared_context.py
d1_client/tests/test_baseclient_1_0.py
d1_client/tests/test_baseclient_1_1.py
d1_client/tests/test_baseclient_2_0.py
d1_client/tests/test_cnclient_1_0.py
d1_client/tests/test_cnclient_1_1.py
d1_client/tests/test_cnclient_2_0.py
d1_client/tests/test_d1client.py
d1_client/tests/test_iter_log_record.py
d1_client/tests/test_iter_log_record_multi.py
d1_client/tests/test_iter_object_list_multi.py
d1_client/tests/test_iter_sysmeta_multi.py
d1_client/tests/test_mnclient_1_0.py
d1_client/tests/test_mnclient_1_1.py
d1_client/tests/test_mnclient_2_0.py
d1_client/tests/test_session.py
d1_client/tests/test_solr_client.py
d1_client/tests/test_util.py
dataone.libclient-3.5.2.dist-info/METADATA
dataone.libclient-3.5.2.dist-info/WHEEL
dataone.libclient-3.5.2.dist-info/top_level.txt
dataone.libclient-3.5.2.dist-info/RECORD
