Metadata-Version: 2.1
Name: dataone.libclient
Version: 3.5.2
Summary: A DataONE client library for Python
Home-page: https://github.com/DataONEorg/d1_python
Author: DataONE Project
Author-email: developers@dataone.org
License: Apache License, Version 2.0
Keywords: DataONE client upload download member-node coordinating-node
Classifier: Development Status :: 5 - Production/Stable
Classifier: Intended Audience :: Developers
Classifier: Topic :: Scientific/Engineering
Classifier: License :: OSI Approved :: Apache Software License
Classifier: Programming Language :: Python :: 3
Classifier: Programming Language :: Python :: 3.7
Requires-Dist: dataone.common (>=3.5.2)
Requires-Dist: pyxb-x (>=1.2.6.1)
Requires-Dist: requests-toolbelt (>=1.0.0)
Requires-Dist: requests[security] (>=2.31.0)
Requires-Dist: aiohttp (>=3.8.4)
